msg_parser/__init__.py
msg_parser/__version__.py
msg_parser/cli.py
msg_parser/data_models.py
msg_parser/email_builder.py
msg_parser/msg_parser.py
msg_parser/properties/__init__.py
msg_parser/properties/ms_exchange_props.txt
msg_parser/properties/ms_props_date_type_map.py
msg_parser/properties/ms_props_generator.py
msg_parser/properties/ms_props_id_map.py
msg_parser/properties/ms_props_master.json
msg_parser-1.2.0.dist-info/AUTHORS.rst
msg_parser-1.2.0.dist-info/LICENSE
msg_parser-1.2.0.dist-info/METADATA
msg_parser-1.2.0.dist-info/WHEEL
msg_parser-1.2.0.dist-info/entry_points.txt
msg_parser-1.2.0.dist-info/top_level.txt
msg_parser-1.2.0.dist-info/RECORD
