Metadata-Version: 2.1
Name: msg-parser
Version: 1.2.0
Summary: This module enables reading, parsing and converting Microsoft Outlook MSG E-Mail files.
Home-page: https://github.com/vikramarsid/msg_parser
Author: Vikram Arsid
Author-email: vikramarsid@gmail.com
License: BSD
Keywords: msg_parser
Platform: UNKNOWN
Classifier: Development Status :: 2 - Pre-Alpha
Classifier: Topic :: Communications
Classifier: Intended Audience :: Developers
Classifier: License :: OSI Approved :: BSD License
Classifier: Natural Language :: English
Classifier: Programming Language :: Python :: 3
Classifier: Programming Language :: Python :: 3.4
Classifier: Programming Language :: Python :: 3.5
Classifier: Programming Language :: Python :: 3.6
Classifier: Programming Language :: Python :: 3.7
Classifier: Programming Language :: Python :: Implementation :: CPython
Requires-Python: >=3.4
Provides-Extra: rtf
